trelia/__init__.py
trelia/reviewer.py
trelia/data/code_signals.json
trelia/data/spam_patterns.json
trelia-0.3.3.dist-info/METADATA
trelia-0.3.3.dist-info/WHEEL
trelia-0.3.3.dist-info/top_level.txt
trelia-0.3.3.dist-info/RECORD
