Metadata-Version: 2.1
Name: trelia
Version: 0.3.3
Summary: A Python package to rate and review student code using different llm's
Home-page: https://www.aegletek.com/
Author: Aegletek
Author-email: coe@aegletek.com
License: MIT
Classifier: Programming Language :: Python :: 3
Classifier: License :: OSI Approved :: MIT License
Classifier: Operating System :: OS Independent
Classifier: Intended Audience :: Developers
Requires-Python: >=3.7
Requires-Dist: google-generativeai
Requires-Dist: kynex
